{
  "name":"Anime Token List",
  "version":{
    "major":5,
    "minor":3,
    "patch":2
  },
  "logoURI":"",
  "keywords":[
    "tokens"
  ],
  "timestamp":"2025-10-15T10:00:00Z",
  "tokens": [
    {
      "name": "Wrapped Anime",
      "decimals": 18,
      "symbol": "WANIME",
      "address": "0x164906a76f1a2ea933366c446ae0ec6a37062c42",
      "chainId": 69000,
      "logoURI": "https://raw.githubusercontent.com/protofire/token-list/main/assets/WANIME.jpg"
    },
    {
      "name": "Wrapped Anime",
      "decimals": 18,
      "symbol": "USDT",
      "address": "0x0000000000000000000000000000000000000000",
      "chainId": 69000,
      "logoURI": "https://raw.githubusercontent.com/protofire/token-list/main/assets/USDT.png"
    },
    {
      "name": "Bridged USDC",
      "decimals": 18,
      "symbol": "USDC.e",
      "address": "0x401ecb1d350407f13ba348573e5630b83638e30d",
      "chainId": 69000,
      "logoURI": "https://raw.githubusercontent.com/protofire/token-list/main/assets/USDC.png"
    }
  ]
}
